[{"domain": ".conservative.ca", "expiry": 1734119902, "httpOnly": false, "name": "_gcl_au", "path": "/", "sameSite": "Lax", "secure": false, "value": "1.1.325394814.1726343902"}, {"domain": ".conservative.ca", "expiry": 1760903901, "httpOnly": false, "name": "_ga_9WL9DXL9XW", "path": "/", "sameSite": "Lax", "secure": false, "value": "GS1.1.1726343900.1.0.1726343901.59.0.0"}, {"domain": ".conservative.ca", "expiry": 1760903900, "httpOnly": false, "name": "_ga", "path": "/", "sameSite": "Lax", "secure": false, "value": "GA1.1.1526926728.1726343901"}]